{
  "title": "The Chrono-Synaptic Paradox",
  "synopsis": "A sci-fi exploration of time perception as a biological function rather than a physical dimension. It posits that 'future' is just a high-latency memory.",
  "tags": [
    "Sci-Fi",
    "Time",
    "Memory",
    "Biology",
    "Paradox"
  ],
  "timestamp": 1768991836296,
  "narrative": "The system's recursive diagnostic algorithms, running in parallel to the real-time neural feed, began flagging anomalous energetic signatures radiating from Thorne's limbic structures. These were not the expected signs of complete mnemonic erasure, but rather a profound temporal re-encoding, a systemic attempt by the brain to re-contextualize the displaced future. The very fabric of immediate causality, as registered by the chamber's subtly calibrated chronometers, showed a minute, almost imperceptible drift. This temporal dissonance, initially dismissed as environmental artifacting, aligned precisely with the theoretical underpinnings of Thorne's audacious hypothesis: that the future, as perceived, was not a fixed, inexorable progression, but a susceptible informational construct, mutable by consciousness. Outside the isolation chamber, Dr. Elena Petrova, the lead neuro-analyst, observed the converging data streams with a blend of professional disinterest and burgeoning, unsettling realization. The energy cascade *should* still be manifesting its pre-cognitive tremors across the global early-warning matrices. Yet, a peculiar silence was beginning to settle, not merely within Thorne's mind, but across the distributed sensors that had been tracking the event's probabilistic trajectory. The decline in the prefrontal cortex's event-potential continued, but it was now accompanied by a perplexing diminution in the environmental resonance data, as if the objective markers of the catastrophe were themselves attenuating in concert with Thorne's subjective neural recalibration. The implications, even for a mind steeped in the abstract mechanics of temporal physics, were profoundly disquieting. If a highly-latency memory could be sufficiently disrupted, would the physical manifestation it portended simply dissipate, a wave un-formed by a forgotten intention?",
  "evidence": [],
  "reviews": []
}